polyrus/__init__.py
polyrus/geometry.py
polyrus/io.py
polyrus-0.0.1.dist-info/METADATA
polyrus-0.0.1.dist-info/WHEEL
polyrus-0.0.1.dist-info/top_level.txt
polyrus-0.0.1.dist-info/RECORD
