Metadata-Version: 2.1
Name: polyrus
Version: 0.0.1
Summary: Geometric library for deep learning on 3D data structures
Author-email: Benedikt Scheffler <scheffler.benedikt@googlemail.com>
Project-URL: homepage, https://github.com/bensch98/polyrus
Project-URL: documentation, https://polyrus.github.io/
Project-URL: repository, https://github.com/bensch98/polyrus
Classifier: License :: OSI Approved :: MIT License
Classifier: Topic :: Scientific/Engineering
Classifier: Topic :: Scientific/Engineering :: Artificial Intelligence
Classifier: Programming Language :: Python :: 3
Classifier: Programming Language :: Python :: 3.8
Classifier: Programming Language :: Python :: 3.9
Classifier: Programming Language :: Python :: 3.10
Classifier: Programming Language :: Python :: 3.11
Requires-Python: >=3.8
Requires-Dist: numpy
Requires-Dist: open3d
Provides-Extra: dev
Requires-Dist: sphinx ; extra == 'dev'
Requires-Dist: ruff ; extra == 'dev'
